{"kind":"identitytoolkit#DownloadAccountResponse","users":[{"localId":"h0UvvQRHiQuOmeZHTeJUHHGrMcmI","displayName":"Mountain Panda","screenName":"panda_mountain","email":"mountain.panda.437@example.com","emailVerified":true,"createdAt":"1690388776395","lastLoginAt":"1690388804535","providerUserInfo":[{"providerId":"google.com","rawId":"1735058974854616570437946026803034554958","federatedId":"1735058974854616570437946026803034554958","displayName":"Mountain Panda","email":"mountain.panda.437@example.com","screenName":"panda_mountain"}],"lastRefreshAt":"2023-07-26T17:38:12.260Z"}]}